aurora_signature-3.15.dist-info/top_level.txt
aurora_signature-3.15.dist-info/RECORD
aurora_signature-3.15.dist-info/entry_points.txt
aurora_signature-3.15.dist-info/METADATA
aurora_signature-3.15.dist-info/WHEEL
aurora_signature/sign.cpython-312-x86_64-linux-musl.so
aurora_signature/service.cpython-312-x86_64-linux-musl.so
aurora_signature/__init__.py
aurora_signature/timestamp.cpython-312-x86_64-linux-musl.so
aurora_signature/AuroraSign/__init__.py
aurora_signature/AuroraSign/aurora_signature/stamp.py
aurora_signature/AuroraSign/aurora_signature/keys.py
aurora_signature/AuroraSign/aurora_signature/__init__.py
aurora_signature/AuroraSign/aurora_signature/version.py
aurora_signature/AuroraSign/aurora_signature/sign/pkcs11.py
aurora_signature/AuroraSign/aurora_signature/sign/fields.py
aurora_signature/AuroraSign/aurora_signature/sign/__init__.py
aurora_signature/AuroraSign/aurora_signature/sign/attributes.py
aurora_signature/AuroraSign/aurora_signature/sign/general.py
aurora_signature/AuroraSign/aurora_signature/sign/timestamps/requests_client.py
aurora_signature/AuroraSign/aurora_signature/sign/timestamps/__init__.py
aurora_signature/AuroraSign/aurora_signature/sign/timestamps/api.py
aurora_signature/AuroraSign/aurora_signature/sign/timestamps/common_utils.py
aurora_signature/AuroraSign/aurora_signature/sign/signers/pdf_signer.py
aurora_signature/AuroraSign/aurora_signature/sign/signers/cms_embedder.py
aurora_signature/AuroraSign/aurora_signature/sign/signers/pdf_cms.py
aurora_signature/AuroraSign/aurora_signature/sign/signers/constants.py
aurora_signature/AuroraSign/aurora_signature/sign/signers/pdf_byterange.py
aurora_signature/AuroraSign/aurora_signature/sign/signers/__init__.py
aurora_signature/AuroraSign/aurora_signature/sign/signers/functions.py
aurora_signature/AuroraSign/aurora_signature/sign/ades/report.py
aurora_signature/AuroraSign/aurora_signature/sign/ades/cades_asn1.py
aurora_signature/AuroraSign/aurora_signature/sign/ades/__init__.py
aurora_signature/AuroraSign/aurora_signature/sign/ades/api.py
aurora_signature/AuroraSign/aurora_signature/sign/diff_analysis/commons.py
