Metadata-Version: 2.1
Name: aurora_signature
Version: 3.15
Requires-Python: >=3.6
Requires-Dist: click==8.1.3
Requires-Dist: requests==2.32.3
Requires-Dist: asn1crypto==1.5.1
Requires-Dist: cryptography>=41.0.2
Requires-Dist: uritools==4.0.3
Requires-Dist: oscrypto==1.3.0
Requires-Dist: tzlocal==5.2
Requires-Dist: pytz==2023.3
Requires-Dist: pycryptodome==3.15.0
